py_rawports/__init__.py
py_rawports/transport.py
py_rawports/examples/FileDescriptor.py
py_rawports/examples/FileIO.py
py_rawports/examples/Serial.py
py_rawports/examples/Socket.py
py_rawports/examples/USB.py
py_rawports/interfaces/FileDescriptor.py
py_rawports/interfaces/FileIO.py
py_rawports/interfaces/Serial.py
py_rawports/interfaces/Socket.py
py_rawports/interfaces/USB.py
py_rawports/interfaces/__init__.py
py_rawports-0.0.6.dist-info/licenses/LICENSE
py_rawports-0.0.6.dist-info/METADATA
py_rawports-0.0.6.dist-info/WHEEL
py_rawports-0.0.6.dist-info/top_level.txt
py_rawports-0.0.6.dist-info/RECORD
